{"atualizadoEm":"5/29/2026, 12:55:30 AM","WI":[202622],"WD":{"202622":{"_meta":{"ini":"25/05","fim":"31/05","mes":"mai","ano":2026,"sid":202622},"HS":{"s":[0,0,0,0,0,0,0],"c":[0,0,0,0,0,0,0],"tot":0,"tot_c":0,"acum":0,"acum_c":0,"ms":0,"mm":0,"pct":0},"VO":{"s":[0,0,0,0,0,0,0],"c":[0,0,0,0,0,0,0],"tot":0,"tot_c":0,"acum":0,"acum_c":0,"ms":0,"mm":0,"pct":0},"MO":{"s":[0,0,0,0,0,0,0],"c":[0,0,0,0,0,0,0],"tot":0,"tot_c":0,"acum":0,"acum_c":0,"ms":0,"mm":0,"pct":0},"TT":{"s":[0,0,0,0,0,0,0],"c":[0,0,0,0,0,0,0],"tot":0,"tot_c":0,"acum":0,"acum_c":0,"ms":0,"mm":0,"pct":0},"JD":{"s":[0,0,0,0,0,0,0],"c":[0,0,0,0,0,0,0],"tot":0,"tot_c":0,"acum":0,"acum_c":0,"ms":0,"mm":0,"pct":0},"CP":{"s":[0,0,0,0,0,0,0],"c":[0,0,0,0,0,0,0],"tot":0,"tot_c":0,"acum":0,"acum_c":0,"ms":0,"mm":0,"pct":0}}},"metasAcmp":{"2026":[{"l":"Jan.","cur":false,"HS":0,"VO":0,"MO":0,"TT":0,"JD":0,"CP":0,"G":0},{"l":"Fev.","cur":false,"HS":0,"VO":0,"MO":0,"TT":0,"JD":0,"CP":0,"G":0},{"l":"Mar","cur":false,"HS":0,"VO":0,"MO":0,"TT":0,"JD":0,"CP":0,"G":0},{"l":"Abr","cur":false,"HS":0,"VO":0,"MO":0,"TT":0,"JD":0,"CP":0,"G":0},{"l":"Mai","cur":true,"HS":null,"VO":null,"MO":null,"TT":null,"JD":null,"CP":null,"G":null},{"l":"Jun","cur":false,"HS":null,"VO":null,"MO":null,"TT":null,"JD":null,"CP":null,"G":null},{"l":"Jul","cur":false,"HS":null,"VO":null,"MO":null,"TT":null,"JD":null,"CP":null,"G":null},{"l":"Ago","cur":false,"HS":null,"VO":null,"MO":null,"TT":null,"JD":null,"CP":null,"G":null},{"l":"Set","cur":false,"HS":null,"VO":null,"MO":null,"TT":null,"JD":null,"CP":null,"G":null},{"l":"Out","cur":false,"HS":null,"VO":null,"MO":null,"TT":null,"JD":null,"CP":null,"G":null},{"l":"Nov","cur":false,"HS":null,"VO":null,"MO":null,"TT":null,"JD":null,"CP":null,"G":null},{"l":"Dez","cur":false,"HS":null,"VO":null,"MO":null,"TT":null,"JD":null,"CP":null,"G":null}]},"pctAno":{"HS":0,"VO":0,"MO":0,"TT":0,"JD":0,"CP":0,"G":0},"recordes":{"diario":{"periodo":"45885","quantidade":270},"semanal":{"periodo":"46132","quantidade":827},"mensal":{"periodo":"45870","quantidade":3036}}}